sanic_jwt/__init__.py
sanic_jwt/authentication.py
sanic_jwt/base.py
sanic_jwt/cache.py
sanic_jwt/claim.py
sanic_jwt/configuration.py
sanic_jwt/decorators.py
sanic_jwt/endpoints.py
sanic_jwt/exceptions.py
sanic_jwt/initialization.py
sanic_jwt/responses.py
sanic_jwt/utils.py
sanic_jwt/validators.py
sanic_jwt-1.8.0.dist-info/LICENSE
sanic_jwt-1.8.0.dist-info/METADATA
sanic_jwt-1.8.0.dist-info/WHEEL
sanic_jwt-1.8.0.dist-info/top_level.txt
sanic_jwt-1.8.0.dist-info/RECORD
