Metadata-Version: 2.1
Name: sanic-jwt
Version: 1.8.0
Summary: JWT oauth flow for Sanic
Home-page: https://github.com/ahopkins/sanic-jwt
Author: Adam Hopkins
Author-email: admhpkns@gmail.com
License: MIT
Download-URL: https://github.com/ahopkins/sanic-jwt/archive/master.zip
Keywords: sanic oauth authentication jwt
Platform: UNKNOWN
Classifier: Development Status :: 5 - Production/Stable
Classifier: Intended Audience :: Developers
Classifier: License :: OSI Approved :: MIT License
Classifier: Programming Language :: Python :: 3
Classifier: Programming Language :: Python :: 3.7
Classifier: Programming Language :: Python :: 3.8
Classifier: Programming Language :: Python :: 3.9
Provides-Extra: docs
Provides-Extra: all
License-File: LICENSE
